LICENSE
README.md
setup.py
owlsimilarity/__init__.py
owlsimilarity/especial_sim_caminhos.py
owlsimilarity/funcoes_aux.py
owlsimilarity/funcoes_ic.py
owlsimilarity/funcoes_relatedness.py
owlsimilarity/funcoes_similarity.py
owlsimilarity/master.py
owlsimilarity/relatedness_measures.py
owlsimilarity/sim_caminhos.py
owlsimilarity/sim_hibrid.py
owlsimilarity/sim_info_content.py
owlsimilarity.egg-info/PKG-INFO
owlsimilarity.egg-info/SOURCES.txt
owlsimilarity.egg-info/dependency_links.txt
owlsimilarity.egg-info/requires.txt
owlsimilarity.egg-info/top_level.txt